{
  "requires": ["java", "exhibitor"],
  "sources": {
    "metronome": {
      "kind": "url_extract",
        "url": "https://downloads.mesosphere.com/maven/dcos/metronome/0.2.0/metronome-0.2.0.tgz",
        "sha1": "256e0a93d75c7a8243e4f9dd155ff7fb9ebbb36e"
    },
    "metronome-plugins": {
      "kind": "url",
      "url": "https://downloads.mesosphere.com/marathon-plugins/marathon-dcos-plugins/1.1.0/plugins.zip",
      "sha1": "a0719fed689f3e910d10ac958a57f787fc206f4b"
    },
    "metronome-plugin-conf": {
      "kind": "url",
      "url": "https://downloads.mesosphere.com/marathon-plugins/marathon-dcos-plugins/1.1.0/plugin-conf.json",
      "sha1": "ad1af05322b6adff27f0c8fd0edbde763327be6f"
    }
  },
  "username": "dcos_metronome"
}
